paracelsus/__init__.py
paracelsus/_version.py
paracelsus/cli.py
paracelsus/config.py
paracelsus/graph.py
paracelsus/pyproject.py
paracelsus/compat/__init__.py
paracelsus/compat/pydot_compat.py
paracelsus/transformers/__init__.py
paracelsus/transformers/dot.py
paracelsus/transformers/mermaid.py
paracelsus/transformers/utils.py
paracelsus-0.15.0.dist-info/licenses/LICENSE
scripts/test_pydot_versions.sh
paracelsus-0.15.0.dist-info/METADATA
paracelsus-0.15.0.dist-info/WHEEL
paracelsus-0.15.0.dist-info/entry_points.txt
paracelsus-0.15.0.dist-info/top_level.txt
paracelsus-0.15.0.dist-info/RECORD
