Metadata-Version: 2.4
Name: paracelsus
Version: 0.15.0
Summary: Visualize SQLAlchemy Databases using Mermaid or Dot Diagrams.
Author: Robert Hafner
License: MIT License
Requires-Python: >=3.10
License-File: LICENSE
Requires-Dist: pydot<5.0,>=3.0
Requires-Dist: packaging
Requires-Dist: sqlalchemy
Requires-Dist: typer
Requires-Dist: toml; python_version < "3.11"
Provides-Extra: dev
Requires-Dist: build; extra == "dev"
Requires-Dist: dapperdata; extra == "dev"
Requires-Dist: glom; extra == "dev"
Requires-Dist: mypy; extra == "dev"
Requires-Dist: pip-tools; extra == "dev"
Requires-Dist: pytest; extra == "dev"
Requires-Dist: pytest-cov; extra == "dev"
Requires-Dist: pytest-pretty; extra == "dev"
Requires-Dist: ruamel.yaml; extra == "dev"
Requires-Dist: ruff; extra == "dev"
Requires-Dist: toml-sort; extra == "dev"
Dynamic: license-file
